dokkusd/__init__.py
dokkusd/cli.py
dokkusd/config_models.py
dokkusd/deploy.py
dokkusd/destroy.py
dokkusd/util.py
DokkuSD-0.6.0.dist-info/LICENSE
DokkuSD-0.6.0.dist-info/METADATA
DokkuSD-0.6.0.dist-info/WHEEL
DokkuSD-0.6.0.dist-info/top_level.txt
DokkuSD-0.6.0.dist-info/RECORD
